{"requests": ["wikidata", "labels", "restbase"], "labels": {"P495": "country of origin", "P571": "inception", "P31": "instance of", "Q1156": "Mumbai", "P3912": "newspaper format", "P407": "language of work or name", "P6157": "Google News publication ID", "Q668": "India", "P1476": "title", "Q665319": "broadsheet", "P159": "headquarters location", "Q1860": "English", "P856": "official website", "P2896": "publication interval", "Q11032": "newspaper", "P2088": "Crunchbase organization ID"}, "wikidata": {"instance of (P31)": "newspaper (Q11032)", "inception (P571)": "+2017-00-00T00:00:00Z", "country of origin (P495)": "India (Q668)", "headquarters location (P159)": "Mumbai (Q1156)", "title (P1476)": "The Time Reports", "newspaper format (P3912)": "broadsheet (Q665319)", "language of work or name (P407)": "English (Q1860)", "official website (P856)": "https://www.thetimereports.com", "publication interval (P2896)": {"amount": "+1", "unit": "http://www.wikidata.org/entity/Q573"}, "Crunchbase organization ID (P2088)": "the-time-reports", "Google News publication ID (P6157)": "CAAqBwgKMJGmnAswpbC0Aw"}, "wikidata_pageid": 99692349, "aliases": ["thetimereports", "thetimereports.com", "TTR", "THE TIME REPORTS"], "modified": {"wikidata": "2022-05-13T11:23:41Z"}, "wikibase": "Q104244424", "wikidata_url": "https://www.wikidata.org/wiki/Q104244424", "description": "Newspaper", "label": "The Time Reports", "claims": {"P31": ["Q11032"], "P571": ["+2017-00-00T00:00:00Z"], "P495": ["Q668"], "P159": ["Q1156"], "P1476": ["The Time Reports"], "P3912": ["Q665319"], "P407": ["Q1860"], "P856": ["https://www.thetimereports.com"], "P2896": [{"amount": "+1", "unit": "http://www.wikidata.org/entity/Q573"}], "P2088": ["the-time-reports"], "P6157": ["CAAqBwgKMJGmnAswpbC0Aw"]}, "title": "The_Time_Reports", "what": "newspaper", "sitelinks": {}}