{"requests": ["wikidata", "labels", "restbase"], "labels": {"P580": "start time", "P31": "instance of", "P407": "language of work or name", "P17": "country", "Q8798": "Ukrainian", "Q212": "Ukraine", "P131": "located in the administrative territorial entity", "P856": "official website", "P2671": "Google Knowledge Graph ID", "Q146453": "Kalush", "Q11032": "newspaper"}, "wikidata": {"instance of (P31)": "newspaper (Q11032)", "official website (P856)": "https://vikna.if.ua/", "country (P17)": "Ukraine (Q212)", "located in the administrative territorial entity (P131)": "Kalush (Q146453)", "start time (P580)": "+2003-00-00T00:00:00Z", "language of work or name (P407)": "Ukrainian (Q8798)", "Google Knowledge Graph ID (P2671)": "/g/120p556h"}, "wikidata_pageid": 13313173, "modified": {"wikidata": "2022-12-07T18:08:47Z"}, "wikibase": "Q12093155", "wikidata_url": "https://www.wikidata.org/wiki/Q12093155", "description": "Ukrainian newspaper", "label": "Vikna", "claims": {"P31": ["Q11032"], "P856": ["https://vikna.if.ua/"], "P17": ["Q212"], "P131": ["Q146453"], "P580": ["+2003-00-00T00:00:00Z"], "P407": ["Q8798"], "P2671": ["/g/120p556h"]}, "title": "Vikna", "what": "newspaper", "sitelinks": {"ukwiki": {"site": "ukwiki", "title": "\u0412\u0456\u043a\u043d\u0430 (\u0433\u0430\u0437\u0435\u0442\u0430)", "badges": []}}}