{"requests": ["wikidata", "labels", "imageinfo", "restbase"], "labels": {"P571": "inception", "P31": "instance of", "P407": "language of work or name", "P625": "coordinate location", "P17": "country", "P1343": "described by source", "Q159": "Russia", "P5008": "on focus list of Wikimedia project", "Q68235346": "WikiProject Q68235346", "Q73357989": "Survey of GLAM open access policy and practice", "P373": "Commons category", "P856": "official website", "P1612": "Commons Institution page", "P2671": "Google Knowledge Graph ID", "P18": "image", "Q7737": "Russian", "Q11032": "newspaper"}, "wikidata": {"Commons category (P373)": "Pereslavl Week (newspaper)", "Commons Institution page (P1612)": "Pereslavl Week", "image (P18)": "Pn-house-newspaper-2000-01.jpg", "instance of (P31)": "newspaper (Q11032)", "inception (P571)": "+1930-09-14T00:00:00Z", "official website (P856)": "http://www.pereslavl.ru/pn/", "language of work or name (P407)": "Russian (Q7737)", "coordinate location (P625)": {"latitude": 56.75095, "longitude": 38.87284, "altitude": null, "precision": 1e-06, "globe": "http://www.wikidata.org/entity/Q2"}, "on focus list of Wikimedia project (P5008)": "WikiProject Q68235346 (Q68235346)", "described by source (P1343)": "Survey of GLAM open access policy and practice (Q73357989)", "Google Knowledge Graph ID (P2671)": "/g/11dyjmmdv", "country (P17)": "Russia (Q159)"}, "wikidata_pageid": 17897211, "modified": {"wikidata": "2022-03-01T11:07:43Z"}, "wikibase": "Q16271771", "wikidata_url": "https://www.wikidata.org/wiki/Q16271771", "description": "Russian newspaper", "label": "Pereslavl Week", "claims": {"P373": ["Pereslavl Week (newspaper)"], "P1612": ["Pereslavl Week"], "P18": ["Pn-house-newspaper-2000-01.jpg"], "P31": ["Q11032"], "P571": ["+1930-09-14T00:00:00Z"], "P856": ["http://www.pereslavl.ru/pn/"], "P407": ["Q7737"], "P625": [{"latitude": 56.75095, "longitude": 38.87284, "altitude": null, "precision": 1e-06, "globe": "http://www.wikidata.org/entity/Q2"}], "P5008": ["Q68235346"], "P1343": ["Q73357989"], "P2671": ["/g/11dyjmmdv"], "P17": ["Q159"]}, "title": "Pereslavl_Week", "image": [{"file": "File:Pn-house-newspaper-2000-01.jpg", "kind": "wikidata-image", "orig": "Pn-house-newspaper-2000-01.jpg", "timestamp": "2012-09-15T00:59:01Z", "size": 85252, "width": 1000, "height": 685, "url": "https://upload.wikimedia.org/wikipedia/commons/5/59/Pn-house-newspaper-2000-01.jpg", "descriptionurl": "https://commons.wikimedia.org/wiki/File:Pn-house-newspaper-2000-01.jpg", "descriptionshorturl": "https://commons.wikimedia.org/w/index.php?curid=21343382", "title": "File:Pn-house-newspaper-2000-01.jpg", "metadata": {"DateTime": {"value": "2012-09-15 00:59:01", "source": "mediawiki-metadata", "hidden": ""}, "ObjectName": {"value": "Pn-house-newspaper-2000-01", "source": "mediawiki-metadata"}, "CommonsMetadataExtension": {"value": 1.2, "source": "extension", "hidden": ""}, "Categories": {"value": "Buildings at Kooperativnaya street (Pereslavl)|Images by Yuri Chastov|Images from the Pereslavl Week by filename|Items with VRTS permission confirmed|PN to translate|Pages with maps|Pereslavl Week (newspaper)|\u041f\u041d \u0444\u043e\u0442\u043e 4 \u0448\u0430\u0433 \u2014 \u0435\u0441\u0442\u044c \u0433\u043e\u0434 \u0438 \u0444\u043e\u0442\u043e\u0433\u0440\u0430\u0444", "source": "commons-categories", "hidden": ""}, "Assessments": {"value": "", "source": "commons-categories", "hidden": ""}, "GPSLatitude": {"value": "56.750864", "source": "commons-desc-page"}, "GPSLongitude": {"value": "38.872944", "source": "commons-desc-page"}, "GPSMapDatum": {"value": "WGS-84", "source": "commons-desc-page", "hidden": ""}, "ImageDescription": {"value": "The building of the newspaper \u00ab<a href=\"https://ru.wikipedia.org/wiki/%D0%9F%D0%B5%D1%80%D0%B5%D1%81%D0%BB%D0%B0%D0%B2%D1%81%D0%BA%D0%B0%D1%8F_%D0%BD%D0%B5%D0%B4%D0%B5%D0%BB%D1%8F\" class=\"extiw\" title=\"ru:\u041f\u0435\u0440\u0435\u0441\u043b\u0430\u0432\u0441\u043a\u0430\u044f \u043d\u0435\u0434\u0435\u043b\u044f\">Pereslavl week</a>\u00bb. Pereslavl, Kooperativnaya street, 72.", "source": "commons-desc-page"}, "DateTimeOriginal": {"value": "2000-08", "source": "commons-desc-page"}, "Credit": {"value": "<bdi><a href=\"https://www.wikidata.org/wiki/Q16271771\" class=\"extiw\" title=\"d:Q16271771\"><span title=\"Russian newspaper\">Pereslavl Week</span></a>\n</bdi>", "source": "commons-desc-page"}, "Artist": {"value": "\u0424\u043e\u0442\u043e\u043a\u043e\u0440\u0440\u0435\u0441\u043f\u043e\u043d\u0434\u0435\u043d\u0442 \u042e. \u041d. \u0427\u0430\u0441\u0442\u043e\u0432", "source": "commons-desc-page"}, "LicenseShortName": {"value": "CC BY-SA 3.0", "source": "commons-desc-page", "hidden": ""}, "UsageTerms": {"value": "Creative Commons Attribution-Share Alike 3.0", "source": "commons-desc-page"}, "AttributionRequired": {"value": "true", "source": "commons-desc-page", "hidden": ""}, "Attribution": {"value": "<br>\u00ab\u041f\u0435\u0440\u0435\u0441\u043b\u0430\u0432\u0441\u043a\u0430\u044f \u043d\u0435\u0434\u0435\u043b\u044f\u00bb / \u042e. \u041d. \u0427\u0430\u0441\u0442\u043e\u0432 / Wikimedia Commons / CC-BY-SA 3.0", "source": "commons-desc-page", "hidden": ""}, "LicenseUrl": {"value": "https://creativecommons.org/licenses/by-sa/3.0", "source": "commons-desc-page"}, "Copyrighted": {"value": "True", "source": "commons-desc-page", "hidden": ""}, "Restrictions": {"value": "", "source": "commons-desc-page", "hidden": ""}, "License": {"value": "cc-by-sa-3.0", "source": "commons-templates", "hidden": ""}}}], "what": "newspaper", "sitelinks": {"commonswiki": {"site": "commonswiki", "title": "Category:Pereslavl Week (newspaper)", "badges": []}, "ruwiki": {"site": "ruwiki", "title": "\u041f\u0435\u0440\u0435\u0441\u043b\u0430\u0432\u0441\u043a\u0430\u044f \u043d\u0435\u0434\u0435\u043b\u044f", "badges": []}, "ruwikinews": {"site": "ruwikinews", "title": "\u041a\u0430\u0442\u0435\u0433\u043e\u0440\u0438\u044f:\u041f\u0435\u0440\u0435\u0441\u043b\u0430\u0432\u0441\u043a\u0430\u044f \u043d\u0435\u0434\u0435\u043b\u044f", "badges": []}}}