{"requests": ["wikidata", "labels", "restbase"], "labels": {"P571": "inception", "P31": "instance of", "P407": "language of work or name", "P646": "Freebase ID", "P3912": "newspaper format", "Q665319": "broadsheet", "P159": "headquarters location", "P856": "official website", "Q13955": "Arabic", "Q40816": "Benghazi", "Q11032": "newspaper"}, "wikidata": {"instance of (P31)": "newspaper (Q11032)", "newspaper format (P3912)": "broadsheet (Q665319)", "inception (P571)": "+2011-01-01T00:00:00Z", "language of work or name (P407)": "Arabic (Q13955)", "headquarters location (P159)": "Benghazi (Q40816)", "Freebase ID (P646)": "/m/0zby3cx", "official website (P856)": "https://www.alkalimaonline.com/"}, "wikidata_pageid": 18611979, "modified": {"wikidata": "2021-07-25T12:06:59Z"}, "wikibase": "Q17007114", "wikidata_url": "https://www.wikidata.org/wiki/Q17007114", "description": "Daily newspaper published in Libya", "label": "Al Kalima", "claims": {"P31": ["Q11032"], "P3912": ["Q665319"], "P571": ["+2011-01-01T00:00:00Z"], "P407": ["Q13955"], "P159": ["Q40816"], "P646": ["/m/0zby3cx"], "P856": ["https://www.alkalimaonline.com/"]}, "title": "Al_Kalima", "what": "newspaper", "sitelinks": {"enwiki": {"site": "enwiki", "title": "Al Kalima", "badges": []}, "itwiki": {"site": "itwiki", "title": "Al Kalima", "badges": []}}, "pageid": 41097830, "exrest": "Al Kalima is an Arabic daily newspaper published in Libya. It is one of the newspapers established during or following the Libyan revolution which toppled Muammar Ghaddafi in 2011.", "exhtml": "<p><i><b>Al Kalima</b></i> is an Arabic daily newspaper published in Libya. It is one of the newspapers established during or following the Libyan revolution which toppled Muammar Ghaddafi in 2011.</p>", "url": "https://en.wikipedia.org/wiki/Al_Kalima", "url_raw": "https://en.wikipedia.org/wiki/Al_Kalima?action=raw"}