{"requests": ["wikidata", "labels", "restbase"], "labels": {"P31": "instance of", "P463": "member of", "Q1008807": "Federal Association of German Advertising journals", "P856": "official website", "P2671": "Google Knowledge Graph ID", "Q11032": "newspaper"}, "wikidata": {"instance of (P31)": "newspaper (Q11032)", "official website (P856)": "http://www.wochenblatt.net", "member of (P463)": "Federal Association of German Advertising journals (Q1008807)", "Google Knowledge Graph ID (P2671)": "/g/11b6jgqg30"}, "wikidata_pageid": 20161864, "modified": {"wikidata": "2022-04-10T06:38:00Z"}, "wikibase": "Q18630771", "wikidata_url": "https://www.wikidata.org/wiki/Q18630771", "description": "weekly newspaper in the district of Konstanz, Germany", "label": "Singener Wochenblatt", "claims": {"P31": ["Q11032"], "P856": ["http://www.wochenblatt.net"], "P463": ["Q1008807"], "P2671": ["/g/11b6jgqg30"]}, "title": "Singener_Wochenblatt", "what": "newspaper", "sitelinks": {"dewiki": {"site": "dewiki", "title": "Singener Wochenblatt", "badges": []}}}