{"requests": ["wikidata", "labels", "restbase"], "labels": {"P495": "country of origin", "P856": "official website", "P407": "language of work or name", "P8687": "social media followers", "P3789": "Telegram username", "Q159": "Russia", "P2397": "YouTube channel ID", "Q11032": "newspaper", "P2002": "Twitter username", "P2013": "Facebook ID", "P3749": "Google Maps Customer ID", "P3185": "VK ID", "P2671": "Google Knowledge Graph ID", "Q1914": "Karelia", "Q1895": "Petrozavodsk", "Q7737": "Russian", "P571": "inception", "P31": "instance of", "P17": "country", "P131": "located in the administrative territorial entity"}, "wikidata": {"instance of (P31)": "newspaper (Q11032)", "inception (P571)": "+1996-00-00T00:00:00Z", "language of work or name (P407)": "Russian (Q7737)", "official website (P856)": ["http://www.rep.ru/", "https://gubdaily.ru/"], "Google Knowledge Graph ID (P2671)": "/g/11bwnd4l_v", "Google Maps Customer ID (P3749)": "12346943586343307193", "country (P17)": "Russia (Q159)", "country of origin (P495)": "Russia (Q159)", "located in the administrative territorial entity (P131)": ["Karelia (Q1914)", "Petrozavodsk (Q1895)"], "VK ID (P3185)": "guberniadaily", "Twitter username (P2002)": "gubernia_daily", "Telegram username (P3789)": "dailykarelia", "YouTube channel ID (P2397)": "UCmjR6opxXtxOmOq9iepXEQQ", "Facebook ID (P2013)": "guberniadaily", "social media followers (P8687)": {"amount": "+6570", "unit": "1", "upperBound": "+6579", "lowerBound": "+6570"}}, "wikidata_pageid": 23680830, "aliases": ["Gubernia Daily", "Karelskaya Guberniya"], "modified": {"wikidata": "2022-12-17T02:36:44Z"}, "wikibase": "Q21640113", "wikidata_url": "https://www.wikidata.org/wiki/Q21640113", "description": "newspaper", "label": "Karelskaya Gubernia", "claims": {"P31": ["Q11032"], "P571": ["+1996-00-00T00:00:00Z"], "P407": ["Q7737"], "P856": ["http://www.rep.ru/", "https://gubdaily.ru/"], "P2671": ["/g/11bwnd4l_v"], "P3749": ["12346943586343307193"], "P17": ["Q159"], "P495": ["Q159"], "P131": ["Q1914", "Q1895"], "P3185": ["guberniadaily"], "P2002": ["gubernia_daily"], "P3789": ["dailykarelia"], "P2397": ["UCmjR6opxXtxOmOq9iepXEQQ"], "P2013": ["guberniadaily"], "P8687": [{"amount": "+6570", "unit": "1", "upperBound": "+6579", "lowerBound": "+6570"}]}, "title": "Karelskaya_Gubernia", "what": "newspaper", "sitelinks": {"ruwiki": {"site": "ruwiki", "title": "\u041a\u0430\u0440\u0435\u043b\u044c\u0441\u043a\u0430\u044f \u0433\u0443\u0431\u0435\u0440\u043d\u0438\u044f", "badges": []}}}