{"requests": ["wikidata", "labels", "restbase"], "labels": {"P3912": "newspaper format", "P2003": "Instagram username", "Q668": "India", "P1476": "title", "P159": "headquarters location", "P856": "official website", "P646": "Freebase ID", "P407": "language of work or name", "P8687": "social media followers", "Q1355": "Bangalore", "P9035": "Muck Rack media outlet ID", "Q11032": "newspaper", "P2002": "Twitter username", "P2013": "Facebook ID", "P2896": "publication interval", "P31": "instance of", "P17": "country", "Q665319": "broadsheet", "Q33673": "Kannada"}, "wikidata": {"instance of (P31)": "newspaper (Q11032)", "official website (P856)": ["http://www.kannadaprabha.com", "https://kannadaprabha.com"], "title (P1476)": "Kannada Prabha", "newspaper format (P3912)": "broadsheet (Q665319)", "language of work or name (P407)": "Kannada (Q33673)", "headquarters location (P159)": "Bangalore (Q1355)", "Instagram username (P2003)": "kannadaprabha", "Facebook ID (P2013)": "kannadaPrabhaOnline", "Twitter username (P2002)": "KannadaPrabha", "publication interval (P2896)": {"amount": "+1", "unit": "http://www.wikidata.org/entity/Q573"}, "Muck Rack media outlet ID (P9035)": "kannadaprabha", "social media followers (P8687)": [{"amount": "+85554", "unit": "1"}, {"amount": "+102740", "unit": "1"}, {"amount": "+115881", "unit": "1"}], "Freebase ID (P646)": "/m/026vkvq", "country (P17)": "India (Q668)"}, "wikidata_pageid": 2283802, "modified": {"wikidata": "2023-02-04T01:38:52Z"}, "wikibase": "Q2363826", "wikidata_url": "https://www.wikidata.org/wiki/Q2363826", "description": "Indian newspaper", "label": "Kannada Prabha", "claims": {"P31": ["Q11032"], "P856": ["http://www.kannadaprabha.com", "https://kannadaprabha.com"], "P1476": ["Kannada Prabha"], "P3912": ["Q665319"], "P407": ["Q33673"], "P159": ["Q1355"], "P2003": ["kannadaprabha"], "P2013": ["kannadaPrabhaOnline"], "P2002": ["KannadaPrabha"], "P2896": [{"amount": "+1", "unit": "http://www.wikidata.org/entity/Q573"}], "P9035": ["kannadaprabha"], "P8687": [{"amount": "+85554", "unit": "1"}, {"amount": "+102740", "unit": "1"}, {"amount": "+115881", "unit": "1"}], "P646": ["/m/026vkvq"], "P17": ["Q668"]}, "title": "Kannada_Prabha", "what": "newspaper", "sitelinks": {"bnwiki": {"site": "bnwiki", "title": "\u0995\u09a8\u09cd\u09a8\u09a1\u09bc \u09aa\u09cd\u09b0\u09ad\u09be", "badges": []}, "enwiki": {"site": "enwiki", "title": "Kannada Prabha", "badges": []}, "knwiki": {"site": "knwiki", "title": "\u0c95\u0ca8\u0ccd\u0ca8\u0ca1\u0caa\u0ccd\u0cb0\u0cad", "badges": []}, "nlwiki": {"site": "nlwiki", "title": "Kannada Prabha", "badges": []}, "tawiki": {"site": "tawiki", "title": "\u0b95\u0ba9\u0bcd\u0ba9\u0b9f\u0baa\u0bcd \u0baa\u0bbf\u0bb0\u0baa\u0bbe", "badges": []}}, "pageid": 8186243, "exrest": "Kannada Prabha is a morning daily jointly owned by Jupiter Capital a company founded by Rajeev Chandrasekhar who is Bharatiya Janata Party\u2019s member of parliament and The New Indian Express Group, is a major Kannada newspaper in Karnataka. The tag line on its masthead is The Most Powerful Kannada Newspaper. It was founded by Ramnath Goenka.", "exhtml": "<p><i><b>Kannada Prabha</b></i> is a morning daily jointly owned by Jupiter Capital a company founded by Rajeev Chandrasekhar who is Bharatiya Janata Party\u2019s member of parliament and <i>The New Indian Express</i> Group, is a major Kannada newspaper in Karnataka. The tag line on its masthead is <i>The Most Powerful Kannada Newspaper</i>. It was founded by Ramnath Goenka.</p>", "url": "https://en.wikipedia.org/wiki/Kannada_Prabha", "url_raw": "https://en.wikipedia.org/wiki/Kannada_Prabha?action=raw", "image": [{"kind": "restbase-original", "width": 254, "height": 385, "url": "https://upload.wikimedia.org/wikipedia/en/6/67/KannadaPrabhaCover.jpg", "file": "KannadaPrabhaCover.jpg"}, {"kind": "restbase-thumb", "width": 254, "height": 385, "url": "https://upload.wikimedia.org/wikipedia/en/6/67/KannadaPrabhaCover.jpg", "file": "KannadaPrabhaCover.jpg"}]}