{"requests": ["wikidata", "labels", "restbase"], "labels": {"P571": "inception", "P407": "language of work or name", "P31": "instance of", "P968": "email address", "Q94473": "I. Ya. Horbachevsky Ternopil National Medical University of Ministry of Health Care of Ukraine", "Q8798": "Ukrainian", "P373": "Commons category", "P856": "official website", "P123": "publisher", "P2896": "publication interval", "P2671": "Google Knowledge Graph ID", "Q11032": "newspaper"}, "wikidata": {"instance of (P31)": "newspaper (Q11032)", "language of work or name (P407)": "Ukrainian (Q8798)", "Commons category (P373)": "Medychna Akademia", "official website (P856)": "http://medychna-akademia.tdmu.edu.ua/", "publisher (P123)": "I. Ya. Horbachevsky Ternopil National Medical University of Ministry of Health Care of Ukraine (Q94473)", "email address (P968)": "mailto:hazeta.univer@gmail.com", "inception (P571)": "+1997-09-30T00:00:00Z", "publication interval (P2896)": {"amount": "+0.5", "unit": "http://www.wikidata.org/entity/Q5151"}, "Google Knowledge Graph ID (P2671)": "/g/11cpf_1khd"}, "wikidata_pageid": 28652254, "modified": {"wikidata": "2022-07-24T01:51:29Z"}, "wikibase": "Q26721132", "wikidata_url": "https://www.wikidata.org/wiki/Q26721132", "description": "newspaper", "label": "Medychna Akademia", "claims": {"P31": ["Q11032"], "P407": ["Q8798"], "P373": ["Medychna Akademia"], "P856": ["http://medychna-akademia.tdmu.edu.ua/"], "P123": ["Q94473"], "P968": ["mailto:hazeta.univer@gmail.com"], "P571": ["+1997-09-30T00:00:00Z"], "P2896": [{"amount": "+0.5", "unit": "http://www.wikidata.org/entity/Q5151"}], "P2671": ["/g/11cpf_1khd"]}, "title": "Medychna_Akademia", "what": "newspaper", "sitelinks": {"commonswiki": {"site": "commonswiki", "title": "Category:Medychna Akademia", "badges": []}, "ukwiki": {"site": "ukwiki", "title": "\u041c\u0435\u0434\u0438\u0447\u043d\u0430 \u0430\u043a\u0430\u0434\u0435\u043c\u0456\u044f", "badges": []}}}