{"requests": ["wikidata", "labels", "restbase"], "labels": {"P571": "inception", "P31": "instance of", "P407": "language of work or name", "Q35493": "Almaty", "P1476": "title", "P159": "headquarters location", "P856": "official website", "P646": "Freebase ID", "Q7737": "Russian", "Q11032": "newspaper"}, "wikidata": {"instance of (P31)": "newspaper (Q11032)", "official website (P856)": "http://www.respublika-kaz.biz/", "inception (P571)": "+2000-00-00T00:00:00Z", "title (P1476)": "\u0420\u0435\u0441\u043f\u0443\u0431\u043b\u0438\u043a\u0430 \u2014 \u0434\u0435\u043b\u043e\u0432\u043e\u0435 \u043e\u0431\u043e\u0437\u0440\u0435\u043d\u0438\u0435", "language of work or name (P407)": "Russian (Q7737)", "headquarters location (P159)": "Almaty (Q35493)", "Freebase ID (P646)": "/m/0616x5"}, "wikidata_pageid": 3542543, "modified": {"wikidata": "2022-07-24T02:07:00Z"}, "wikibase": "Q3716789", "wikidata_url": "https://www.wikidata.org/wiki/Q3716789", "description": "newspaper", "label": "Respublika", "claims": {"P31": ["Q11032"], "P856": ["http://www.respublika-kaz.biz/"], "P571": ["+2000-00-00T00:00:00Z"], "P1476": ["\u0420\u0435\u0441\u043f\u0443\u0431\u043b\u0438\u043a\u0430 \u2014 \u0434\u0435\u043b\u043e\u0432\u043e\u0435 \u043e\u0431\u043e\u0437\u0440\u0435\u043d\u0438\u0435"], "P407": ["Q7737"], "P159": ["Q35493"], "P646": ["/m/0616x5"]}, "title": "Respublika_(Kazakh_newspaper)", "what": "newspaper", "sitelinks": {"azwiki": {"site": "azwiki", "title": "Respublika (q\u0259zet, Qazax\u0131stan)", "badges": []}, "bawiki": {"site": "bawiki", "title": "\u0420\u0435\u0441\u043f\u0443\u0431\u043b\u0438\u043a\u0430 \u2014 \u0434\u0435\u043b\u043e\u0432\u043e\u0435 \u043e\u0431\u043e\u0437\u0440\u0435\u043d\u0438\u0435", "badges": []}, "bewiki": {"site": "bewiki", "title": "\u0420\u0435\u0441\u043f\u0443\u0431\u043b\u0438\u043a\u0430 \u2014 \u0434\u0435\u043b\u043e\u0432\u043e\u0435 \u043e\u0431\u043e\u0437\u0440\u0435\u043d\u0438\u0435", "badges": []}, "enwiki": {"site": "enwiki", "title": "Respublika (Kazakh newspaper)", "badges": []}, "kkwiki": {"site": "kkwiki", "title": "\u0420\u0435\u0441\u043f\u0443\u0431\u043b\u0438\u043a\u0430 (\u0433\u0430\u0437\u0435\u0442)", "badges": []}, "ruwiki": {"site": "ruwiki", "title": "\u0420\u0435\u0441\u043f\u0443\u0431\u043b\u0438\u043a\u0430 \u2014 \u0434\u0435\u043b\u043e\u0432\u043e\u0435 \u043e\u0431\u043e\u0437\u0440\u0435\u043d\u0438\u0435", "badges": []}, "trwiki": {"site": "trwiki", "title": "Respublika (Kazak gazetesi)", "badges": []}, "ukwiki": {"site": "ukwiki", "title": "\u0420\u0435\u0441\u043f\u0443\u0431\u043b\u0456\u043a\u0430 (\u0433\u0430\u0437\u0435\u0442\u0430)", "badges": []}}}