{"requests": ["wikidata", "labels", "restbase"], "labels": {"P571": "inception", "P31": "instance of", "P407": "language of work or name", "Q19660": "Bucharest", "Q7913": "Romanian", "P1476": "title", "P159": "headquarters location", "P856": "official website", "P646": "Freebase ID", "Q11032": "newspaper"}, "wikidata": {"instance of (P31)": "newspaper (Q11032)", "official website (P856)": "http://www.dreptatea.ro/", "inception (P571)": "+1927-10-17T00:00:00Z", "title (P1476)": "Dreptatea", "language of work or name (P407)": "Romanian (Q7913)", "headquarters location (P159)": "Bucharest (Q19660)", "Freebase ID (P646)": "/m/0h54wcr"}, "wikidata_pageid": 5075375, "modified": {"wikidata": "2021-12-31T15:31:01Z"}, "wikibase": "Q5306979", "wikidata_url": "https://www.wikidata.org/wiki/Q5306979", "description": "Romanian newspaper (1927-1947)", "label": "Dreptatea", "claims": {"P31": ["Q11032"], "P856": ["http://www.dreptatea.ro/"], "P571": ["+1927-10-17T00:00:00Z"], "P1476": ["Dreptatea"], "P407": ["Q7913"], "P159": ["Q19660"], "P646": ["/m/0h54wcr"]}, "title": "Dreptatea", "what": "newspaper", "sitelinks": {"enwiki": {"site": "enwiki", "title": "Dreptatea", "badges": []}, "rowiki": {"site": "rowiki", "title": "Dreptatea", "badges": []}}, "pageid": 33037803, "exrest": "Dreptatea was a Romanian newspaper that appeared between 17 October 1927 and 17 July 1947, as a newspaper of the National Peasants' Party. It was re-founded on February 5, 1990 as a publication of the Christian-Democratic National Peasants' Party (Romania).", "exhtml": "<p><i><b>Dreptatea</b></i> was a Romanian newspaper that appeared between 17 October 1927 and 17 July 1947, as a newspaper of the National Peasants' Party. It was re-founded on February 5, 1990 as a publication of the Christian-Democratic National Peasants' Party (Romania).</p>", "url": "https://en.wikipedia.org/wiki/Dreptatea", "url_raw": "https://en.wikipedia.org/wiki/Dreptatea?action=raw"}