{"requests": ["wikidata", "labels", "restbase"], "labels": {"P5603": "Trove newspaper ID", "P571": "inception", "P31": "instance of", "P495": "country of origin", "P2002": "Twitter username", "P3912": "newspaper format", "P580": "start time", "Q408": "Australia", "P291": "place of publication", "Q17856": "Ballarat", "P8687": "social media followers", "P1476": "title", "Q1449648": "tabloid", "P856": "official website", "P646": "Freebase ID", "Q1002697": "periodical", "Q11032": "newspaper"}, "wikidata": {"instance of (P31)": ["newspaper (Q11032)", "periodical (Q1002697)"], "title (P1476)": "Evening Echo", "inception (P571)": "+1892-00-00T00:00:00Z", "newspaper format (P3912)": "tabloid (Q1449648)", "place of publication (P291)": "Ballarat (Q17856)", "Trove newspaper ID (P5603)": "1325", "country of origin (P495)": "Australia (Q408)", "official website (P856)": "https://www.echolive.ie/", "Twitter username (P2002)": "echolivecork", "social media followers (P8687)": [{"amount": "+71170", "unit": "1"}, {"amount": "+67317", "unit": "1"}, {"amount": "+76575", "unit": "1"}, {"amount": "+81739", "unit": "1"}], "Freebase ID (P646)": "/m/0960lp", "start time (P580)": "+1892-00-00T00:00:00Z"}, "wikidata_pageid": 5180766, "aliases": ["Evening Echo", "EchoLive.ie"], "modified": {"wikidata": "2023-02-03T12:31:21Z"}, "wikibase": "Q5416601", "wikidata_url": "https://www.wikidata.org/wiki/Q5416601", "description": "Irish morning newspaper based in Cork", "label": "The Echo", "claims": {"P31": ["Q11032", "Q1002697"], "P1476": ["Evening Echo"], "P571": ["+1892-00-00T00:00:00Z"], "P3912": ["Q1449648"], "P291": ["Q17856"], "P5603": ["1325"], "P495": ["Q408"], "P856": ["https://www.echolive.ie/"], "P2002": ["echolivecork"], "P8687": [{"amount": "+71170", "unit": "1"}, {"amount": "+67317", "unit": "1"}, {"amount": "+76575", "unit": "1"}, {"amount": "+81739", "unit": "1"}], "P646": ["/m/0960lp"], "P580": ["+1892-00-00T00:00:00Z"]}, "title": "The_Echo_(Cork_newspaper)", "what": "newspaper", "sitelinks": {"enwiki": {"site": "enwiki", "title": "The Echo (Cork newspaper)", "badges": []}, "gawiki": {"site": "gawiki", "title": "Evening Echo", "badges": []}, "plwiki": {"site": "plwiki", "title": "Evening Echo", "badges": []}}, "pageid": 3327567, "exrest": "The Echo, formerly known as the Evening Echo, is an Irish morning newspaper based in Cork. It is distributed throughout the province of Munster, although it is primarily read in its base city of Cork. The newspaper was founded as a broadsheet in 1892, and has been published in tabloid format since 1991.", "exhtml": "<p><i><b>The Echo</b></i>, formerly known as the <i><b>Evening Echo</b></i>, is an Irish morning newspaper based in Cork. It is distributed throughout the province of Munster, although it is primarily read in its base city of Cork. The newspaper was founded as a broadsheet in 1892, and has been published in tabloid format since 1991.</p>", "url": "https://en.wikipedia.org/wiki/The_Echo_(Cork_newspaper)", "url_raw": "https://en.wikipedia.org/wiki/The_Echo_(Cork_newspaper)?action=raw"}