{"requests": ["wikidata", "labels", "restbase"], "labels": {"P4033": "Mastodon address", "P31": "instance of", "Q11032": "newspaper", "P1343": "described by source", "P159": "headquarters location", "Q101246972": "Columbia Journalism Review's Guide to Online News Startups", "P856": "official website", "P2671": "Google Knowledge Graph ID", "Q18575": "Tucson"}, "wikidata": {"instance of (P31)": "newspaper (Q11032)", "headquarters location (P159)": "Tucson (Q18575)", "described by source (P1343)": "Columbia Journalism Review's Guide to Online News Startups (Q101246972)", "Google Knowledge Graph ID (P2671)": "/g/11gjhfrnkh", "Mastodon address (P4033)": "TucsonSentinel@mastodon.tucsonsentinel.com", "official website (P856)": "https://www.tucsonsentinel.com/"}, "wikidata_pageid": 55621743, "aliases": ["TucsonSentinel.com"], "modified": {"wikidata": "2023-03-11T13:11:34Z"}, "wikibase": "Q55636280", "wikidata_url": "https://www.wikidata.org/wiki/Q55636280", "description": "Nonprofit online newspaper in Arizona, US", "label": "Tucson Sentinel", "claims": {"P31": ["Q11032"], "P159": ["Q18575"], "P1343": ["Q101246972"], "P2671": ["/g/11gjhfrnkh"], "P4033": ["TucsonSentinel@mastodon.tucsonsentinel.com"], "P856": ["https://www.tucsonsentinel.com/"]}, "title": "Tucson_Sentinel", "what": "newspaper", "sitelinks": {"enwiki": {"site": "enwiki", "title": "Tucson Sentinel", "badges": []}}, "pageid": 57560638, "exrest": "The Tucson Sentinel is a nonprofit online newspaper in Tucson, founded in 2009 and began publishing full-time in January 2010, with a focus on Arizona and regional news.", "exhtml": "<p>The <i><b>Tucson Sentinel</b></i> is a nonprofit online newspaper in Tucson, founded in 2009 and began publishing full-time in January 2010, with a focus on Arizona and regional news.</p>", "url": "https://en.wikipedia.org/wiki/Tucson_Sentinel", "url_raw": "https://en.wikipedia.org/wiki/Tucson_Sentinel?action=raw"}