{"requests": ["wikidata", "labels", "restbase"], "labels": {"P495": "country of origin", "Q60": "New York City", "P2002": "Twitter username", "P31": "instance of", "P17": "country", "Q88384279": "NYC Community Media", "P2013": "Facebook ID", "P291": "place of publication", "P8687": "social media followers", "P1476": "title", "P127": "owned by", "P4003": "Facebook page ID", "P159": "headquarters location", "P131": "located in the administrative territorial entity", "P856": "official website", "Q30": "United States of America", "P5454": "USNPL ID", "Q11032": "newspaper"}, "wikidata": {"Facebook page ID (P4003)": "Downtown-Express/95648952169", "country of origin (P495)": "United States of America (Q30)", "country (P17)": "United States of America (Q30)", "located in the administrative territorial entity (P131)": "New York City (Q60)", "title (P1476)": "Downtown Express", "USNPL ID (P5454)": "6596", "Twitter username (P2002)": "DOWNTOWNEXPRESS", "place of publication (P291)": "New York City (Q60)", "instance of (P31)": "newspaper (Q11032)", "Facebook ID (P2013)": "Downtown-Express-95648952169", "owned by (P127)": "NYC Community Media (Q88384279)", "official website (P856)": "http://www.downtownexpress.com/", "headquarters location (P159)": "New York City (Q60)", "social media followers (P8687)": {"amount": "+5920", "unit": "1"}}, "wikidata_pageid": 55650784, "modified": {"wikidata": "2021-01-07T05:30:33Z"}, "wikibase": "Q55668354", "wikidata_url": "https://www.wikidata.org/wiki/Q55668354", "description": "newspaper published in New York", "label": "Downtown Express", "claims": {"P4003": ["Downtown-Express/95648952169"], "P495": ["Q30"], "P17": ["Q30"], "P131": ["Q60"], "P1476": ["Downtown Express"], "P5454": ["6596"], "P2002": ["DOWNTOWNEXPRESS"], "P291": ["Q60"], "P31": ["Q11032"], "P2013": ["Downtown-Express-95648952169"], "P127": ["Q88384279"], "P856": ["http://www.downtownexpress.com/"], "P159": ["Q60"], "P8687": [{"amount": "+5920", "unit": "1"}]}, "title": "Downtown_Express", "what": "newspaper", "sitelinks": {}}