{"requests": ["wikidata", "labels", "imageinfo", "restbase"], "labels": {"P571": "inception", "P31": "instance of", "P2002": "Twitter username", "P3912": "newspaper format", "P8687": "social media followers", "P1476": "title", "Q1449648": "tabloid", "P856": "official website", "P646": "Freebase ID", "P18": "image", "Q11032": "newspaper"}, "wikidata": {"instance of (P31)": "newspaper (Q11032)", "official website (P856)": "http://mothersnews.net/", "title (P1476)": "Mothers News", "inception (P571)": "+2010-00-00T00:00:00Z", "newspaper format (P3912)": "tabloid (Q1449648)", "image (P18)": "Mothersnews.jpg", "Twitter username (P2002)": "mothersnews", "Freebase ID (P646)": "/m/0hr2f1x", "social media followers (P8687)": [{"amount": "+1962", "unit": "1"}, {"amount": "+1951", "unit": "1"}]}, "wikidata_pageid": 6776328, "modified": {"wikidata": "2022-07-24T03:33:54Z"}, "wikibase": "Q6917568", "wikidata_url": "https://www.wikidata.org/wiki/Q6917568", "description": "newspaper", "label": "Mothers News", "claims": {"P31": ["Q11032"], "P856": ["http://mothersnews.net/"], "P1476": ["Mothers News"], "P571": ["+2010-00-00T00:00:00Z"], "P3912": ["Q1449648"], "P18": ["Mothersnews.jpg"], "P2002": ["mothersnews"], "P646": ["/m/0hr2f1x"], "P8687": [{"amount": "+1962", "unit": "1"}, {"amount": "+1951", "unit": "1"}]}, "title": "Mothers_News", "image": [{"file": "File:Mothersnews.jpg", "kind": "wikidata-image", "orig": "Mothersnews.jpg", "timestamp": "2011-12-25T06:29:58Z", "size": 111981, "width": 500, "height": 669, "url": "https://upload.wikimedia.org/wikipedia/commons/8/8a/Mothersnews.jpg", "descriptionurl": "https://commons.wikimedia.org/wiki/File:Mothersnews.jpg", "descriptionshorturl": "https://commons.wikimedia.org/w/index.php?curid=17791663", "title": "File:Mothersnews.jpg", "metadata": {"DateTime": {"value": "2011-12-25 06:29:58", "source": "mediawiki-metadata", "hidden": ""}, "ObjectName": {"value": "Mothersnews", "source": "mediawiki-metadata"}, "CommonsMetadataExtension": {"value": 1.2, "source": "extension", "hidden": ""}, "Categories": {"value": "Culture of Rhode Island|Magazines about culture|Magazines of the United States, 2010|Self-published work", "source": "commons-categories", "hidden": ""}, "Assessments": {"value": "", "source": "commons-categories", "hidden": ""}, "ImageDescription": {"value": "First issues of Mothers News", "source": "commons-desc-page"}, "DateTimeOriginal": {"value": "2011-07-21", "source": "commons-desc-page"}, "Credit": {"value": "<span class=\"int-own-work\" lang=\"en\">Own work</span>", "source": "commons-desc-page"}, "Artist": {"value": "<a href=\"//commons.wikimedia.org/w/index.php?title=User:Disbooya&amp;action=edit&amp;redlink=1\" class=\"new\" title=\"User:Disbooya (page does not exist)\">Disbooya</a>", "source": "commons-desc-page"}, "LicenseShortName": {"value": "CC BY-SA 3.0", "source": "commons-desc-page", "hidden": ""}, "UsageTerms": {"value": "Creative Commons Attribution-Share Alike 3.0", "source": "commons-desc-page"}, "AttributionRequired": {"value": "true", "source": "commons-desc-page", "hidden": ""}, "LicenseUrl": {"value": "https://creativecommons.org/licenses/by-sa/3.0", "source": "commons-desc-page"}, "Copyrighted": {"value": "True", "source": "commons-desc-page", "hidden": ""}, "Restrictions": {"value": "", "source": "commons-desc-page", "hidden": ""}, "License": {"value": "cc-by-sa-3.0", "source": "commons-templates", "hidden": ""}}}, {"kind": "restbase-original", "width": 500, "height": 669, "url": "https://upload.wikimedia.org/wikipedia/commons/8/8a/Mothersnews.jpg", "file": "Mothersnews.jpg"}, {"kind": "restbase-thumb", "width": 320, "height": 428, "url": "https://upload.wikimedia.org/wikipedia/commons/thumb/8/8a/Mothersnews.jpg/320px-Mothersnews.jpg", "file": "320px-Mothersnews.jpg"}], "what": "newspaper", "sitelinks": {"enwiki": {"site": "enwiki", "title": "Mothers News", "badges": []}}}