{"requests": ["wikidata", "labels", "restbase"], "labels": {"P571": "inception", "P407": "language of work or name", "P31": "instance of", "P2003": "Instagram username", "P17": "country", "Q7018348": "Oren Zivlin", "Q801": "Israel", "P2013": "Facebook ID", "P127": "owned by", "P856": "official website", "P2671": "Google Knowledge Graph ID", "P98": "editor", "Q11032": "newspaper", "Q9288": "Hebrew"}, "wikidata": {"official website (P856)": ["http://www.mako.co.il/maariv-lanoar", "https://13tv.co.il/maariv-lanoar/"], "country (P17)": "Israel (Q801)", "language of work or name (P407)": "Hebrew (Q9288)", "inception (P571)": "+1957-00-00T00:00:00Z", "instance of (P31)": "newspaper (Q11032)", "Google Knowledge Graph ID (P2671)": "/g/121b1_9z", "Instagram username (P2003)": "maarivlanoar", "Facebook ID (P2013)": "Lanoar", "editor (P98)": "Oren Zivlin (Q7018348)", "owned by (P127)": "Oren Zivlin (Q7018348)"}, "wikidata_pageid": 6933562, "modified": {"wikidata": "2023-04-15T21:02:14Z"}, "wikibase": "Q7045006", "wikidata_url": "https://www.wikidata.org/wiki/Q7045006", "description": "israeli weekly magazine", "label": "Ma'ariv La'noar", "claims": {"P856": ["http://www.mako.co.il/maariv-lanoar", "https://13tv.co.il/maariv-lanoar/"], "P17": ["Q801"], "P407": ["Q9288"], "P571": ["+1957-00-00T00:00:00Z"], "P31": ["Q11032"], "P2671": ["/g/121b1_9z"], "P2003": ["maarivlanoar"], "P2013": ["Lanoar"], "P98": ["Q7018348"], "P127": ["Q7018348"]}, "title": "Ma'ariv_La'noar", "what": "newspaper", "sitelinks": {"enwiki": {"site": "enwiki", "title": "Ma'ariv La'noar", "badges": []}, "hewiki": {"site": "hewiki", "title": "\u05de\u05e2\u05e8\u05d9\u05d1 \u05dc\u05e0\u05d5\u05e2\u05e8", "badges": []}}}