{"requests": ["wikidata", "labels", "restbase"], "labels": {"P571": "inception", "P31": "instance of", "P2002": "Twitter username", "Q847906": "online magazine", "P3912": "newspaper format", "P8687": "social media followers", "P1476": "title", "P159": "headquarters location", "P856": "official website", "Q485176": "Pasadena", "P646": "Freebase ID", "Q11032": "newspaper", "P2088": "Crunchbase organization ID"}, "wikidata": {"instance of (P31)": "newspaper (Q11032)", "official website (P856)": "http://pasadenanow.com/main/", "title (P1476)": "Pasadena Now", "newspaper format (P3912)": "online magazine (Q847906)", "inception (P571)": "+2004-01-01T00:00:00Z", "headquarters location (P159)": "Pasadena (Q485176)", "Twitter username (P2002)": "epasadenanow", "social media followers (P8687)": [{"amount": "+17624", "unit": "1"}, {"amount": "+16150", "unit": "1"}, {"amount": "+18337", "unit": "1"}, {"amount": "+18092", "unit": "1"}], "Freebase ID (P646)": "/m/0h96104", "Crunchbase organization ID (P2088)": "pasadena-now"}, "wikidata_pageid": 7039088, "modified": {"wikidata": "2023-03-07T18:27:28Z"}, "wikibase": "Q7141553", "wikidata_url": "https://www.wikidata.org/wiki/Q7141553", "description": "newspaper", "label": "Pasadena Now", "claims": {"P31": ["Q11032"], "P856": ["http://pasadenanow.com/main/"], "P1476": ["Pasadena Now"], "P3912": ["Q847906"], "P571": ["+2004-01-01T00:00:00Z"], "P159": ["Q485176"], "P2002": ["epasadenanow"], "P8687": [{"amount": "+17624", "unit": "1"}, {"amount": "+16150", "unit": "1"}, {"amount": "+18337", "unit": "1"}, {"amount": "+18092", "unit": "1"}], "P646": ["/m/0h96104"], "P2088": ["pasadena-now"]}, "title": "Pasadena_Now", "what": "newspaper", "sitelinks": {"enwiki": {"site": "enwiki", "title": "Pasadena Now", "badges": []}}}