{"requests": ["wikidata", "labels", "imageinfo", "restbase"], "labels": {"P571": "inception", "P31": "instance of", "P2002": "Twitter username", "P495": "country of origin", "P2013": "Facebook ID", "P291": "place of publication", "Q485172": "Ann Arbor", "P8687": "social media followers", "P1476": "title", "P856": "official website", "Q30": "United States of America", "P646": "Freebase ID", "P18": "image", "P5454": "USNPL ID", "Q11032": "newspaper"}, "wikidata": {"instance of (P31)": "newspaper (Q11032)", "title (P1476)": ["The Ann Arbor News", "Ann Arbor News"], "official website (P856)": "http://www.mlive.com/annarbornews", "inception (P571)": "+1835-00-00T00:00:00Z", "USNPL ID (P5454)": "1475", "Facebook ID (P2013)": "annarbornews", "Twitter username (P2002)": "annarbornews", "country of origin (P495)": "United States of America (Q30)", "place of publication (P291)": "Ann Arbor (Q485172)", "image (P18)": "Ann Arbor News building.tif", "social media followers (P8687)": [{"amount": "+59727", "unit": "1"}, {"amount": "+60527", "unit": "1"}, {"amount": "+61104", "unit": "1"}], "Freebase ID (P646)": "/m/02x0nj8"}, "wikidata_pageid": 7640509, "aliases": ["Ann Arbor News"], "modified": {"wikidata": "2023-02-05T09:06:17Z"}, "wikibase": "Q7713845", "wikidata_url": "https://www.wikidata.org/wiki/Q7713845", "description": "US newspaper", "label": "The Ann Arbor News", "claims": {"P31": ["Q11032"], "P1476": ["The Ann Arbor News", "Ann Arbor News"], "P856": ["http://www.mlive.com/annarbornews"], "P571": ["+1835-00-00T00:00:00Z"], "P5454": ["1475"], "P2013": ["annarbornews"], "P2002": ["annarbornews"], "P495": ["Q30"], "P291": ["Q485172"], "P18": ["Ann Arbor News building.tif"], "P8687": [{"amount": "+59727", "unit": "1"}, {"amount": "+60527", "unit": "1"}, {"amount": "+61104", "unit": "1"}], "P646": ["/m/02x0nj8"]}, "title": "The_Ann_Arbor_News", "image": [{"file": "File:Ann Arbor News building.tif", "kind": "wikidata-image", "orig": "Ann Arbor News building.tif", "timestamp": "2014-06-05T17:51:51Z", "size": 6032454, "width": 1224, "height": 1632, "pagecount": 1, "url": "https://upload.wikimedia.org/wikipedia/commons/6/63/Ann_Arbor_News_building.tif", "descriptionurl": "https://commons.wikimedia.org/wiki/File:Ann_Arbor_News_building.tif", "descriptionshorturl": "https://commons.wikimedia.org/w/index.php?curid=33213349", "title": "File:Ann Arbor News building.tif", "metadata": {"DateTime": {"value": "2014-06-05 17:51:51", "source": "mediawiki-metadata", "hidden": ""}, "ObjectName": {"value": "Ann Arbor News building", "source": "mediawiki-metadata"}, "CommonsMetadataExtension": {"value": 1.2, "source": "extension", "hidden": ""}, "Categories": {"value": "Advance Publications|Built in Michigan in 2008|CC-Zero|Corner buildings in the United States|Downtown Ann Arbor, Michigan|Files with coordinates missing SDC location of creation|FoP-United States|High-rises in Ann Arbor, Michigan|June 2014 in Michigan|Newspapers of Michigan|Pages with maps|Self-published work", "source": "commons-categories", "hidden": ""}, "Assessments": {"value": "", "source": "commons-categories", "hidden": ""}, "GPSLatitude": {"value": "42.281022", "source": "commons-desc-page"}, "GPSLongitude": {"value": "-83.751258", "source": "commons-desc-page"}, "GPSMapDatum": {"value": "WGS-84", "source": "commons-desc-page", "hidden": ""}, "ImageDescription": {"value": "The headquarters of The Ann Arbor News and MLive Media Group (corner of W. Huron and N. Ashley Streets, Ann Arbor, MI)", "source": "commons-desc-page"}, "DateTimeOriginal": {"value": "2014-06-05 13:47:52", "source": "commons-desc-page"}, "Credit": {"value": "<span class=\"int-own-work\" lang=\"en\">Own work</span>", "source": "commons-desc-page"}, "Artist": {"value": "<a href=\"//commons.wikimedia.org/wiki/User:SteveStrummer\" title=\"User:SteveStrummer\">SteveStrummer</a>", "source": "commons-desc-page"}, "LicenseShortName": {"value": "CC0", "source": "commons-desc-page", "hidden": ""}, "UsageTerms": {"value": "Creative Commons Zero, Public Domain Dedication", "source": "commons-desc-page"}, "AttributionRequired": {"value": "false", "source": "commons-desc-page", "hidden": ""}, "LicenseUrl": {"value": "http://creativecommons.org/publicdomain/zero/1.0/deed.en", "source": "commons-desc-page"}, "Copyrighted": {"value": "True", "source": "commons-desc-page", "hidden": ""}, "Restrictions": {"value": "", "source": "commons-desc-page", "hidden": ""}, "License": {"value": "cc0", "source": "commons-templates", "hidden": ""}}}, {"kind": "restbase-original", "width": 1224, "height": 1632, "url": "https://upload.wikimedia.org/wikipedia/commons/thumb/6/63/Ann_Arbor_News_building.tif/lossy-page1-1224px-Ann_Arbor_News_building.tif.jpg", "file": "lossy-page1-1224px-Ann_Arbor_News_building.tif.jpg"}, {"kind": "restbase-thumb", "width": 320, "height": 427, "url": "https://upload.wikimedia.org/wikipedia/commons/thumb/6/63/Ann_Arbor_News_building.tif/lossy-page1-320px-Ann_Arbor_News_building.tif.jpg", "file": "lossy-page1-320px-Ann_Arbor_News_building.tif.jpg"}], "what": "newspaper", "sitelinks": {"enwiki": {"site": "enwiki", "title": "The Ann Arbor News", "badges": []}}}