{"requests": ["wikidata", "labels", "restbase"], "labels": {"P495": "country of origin", "P3912": "newspaper format", "P1476": "title", "Q204561": "Modesto", "P856": "official website", "Q30": "United States of America", "P646": "Freebase ID", "P8507": "Legacy.com newspaper ID", "P463": "member of", "P7259": "Newspapers.com paper ID", "P9852": "Media Bias/Fact Check ID", "P127": "owned by", "Q1660027": "The McClatchy Company", "P3417": "Quora topic ID", "P9035": "Muck Rack media outlet ID", "P5454": "USNPL ID", "Q11032": "newspaper", "P2002": "Twitter username", "P2013": "Facebook ID", "P6136": "Newseum newspaper front page ID", "Q1626261": "Inter American Press Association", "P2088": "Crunchbase organization ID", "P571": "inception", "P31": "instance of", "P17": "country", "P291": "place of publication", "Q665319": "broadsheet", "P131": "located in the administrative territorial entity"}, "wikidata": {"instance of (P31)": "newspaper (Q11032)", "title (P1476)": ["The Modesto Bee", "Modesto Bee"], "official website (P856)": "http://www.modbee.com/", "owned by (P127)": "The McClatchy Company (Q1660027)", "inception (P571)": "+1884-00-00T00:00:00Z", "Quora topic ID (P3417)": "The-Modesto-Bee", "newspaper format (P3912)": "broadsheet (Q665319)", "Twitter username (P2002)": ["modbee", "modbee"], "located in the administrative territorial entity (P131)": "Modesto (Q204561)", "Facebook ID (P2013)": "modestobee", "country of origin (P495)": "United States of America (Q30)", "place of publication (P291)": "Modesto (Q204561)", "country (P17)": "United States of America (Q30)", "USNPL ID (P5454)": "296", "Newseum newspaper front page ID (P6136)": "CA_MB", "member of (P463)": "Inter American Press Association (Q1626261)", "Legacy.com newspaper ID (P8507)": "modestobee", "Newspapers.com paper ID (P7259)": "22659", "Muck Rack media outlet ID (P9035)": "modbee", "Freebase ID (P646)": "/m/0dfnb9", "Media Bias/Fact Check ID (P9852)": "the-modesto-bee", "Crunchbase organization ID (P2088)": "the-modesto-bee"}, "wikidata_pageid": 7680937, "aliases": ["Modesto Bee", "ModBee"], "modified": {"wikidata": "2023-02-07T18:16:31Z"}, "wikibase": "Q7751895", "wikidata_url": "https://www.wikidata.org/wiki/Q7751895", "description": "Newspaper in Modesto, California", "label": "The Modesto Bee", "claims": {"P31": ["Q11032"], "P1476": ["The Modesto Bee", "Modesto Bee"], "P856": ["http://www.modbee.com/"], "P127": ["Q1660027"], "P571": ["+1884-00-00T00:00:00Z"], "P3417": ["The-Modesto-Bee"], "P3912": ["Q665319"], "P2002": ["modbee", "modbee"], "P131": ["Q204561"], "P2013": ["modestobee"], "P495": ["Q30"], "P291": ["Q204561"], "P17": ["Q30"], "P5454": ["296"], "P6136": ["CA_MB"], "P463": ["Q1626261"], "P8507": ["modestobee"], "P7259": ["22659"], "P9035": ["modbee"], "P646": ["/m/0dfnb9"], "P9852": ["the-modesto-bee"], "P2088": ["the-modesto-bee"]}, "title": "The_Modesto_Bee", "what": "newspaper", "sitelinks": {"bnwiki": {"site": "bnwiki", "title": "\u09a6\u09cd\u09af \u09ae\u09cb\u09a1\u09c7\u09b8\u09cd\u099f\u09cb \u09ac\u09bf", "badges": []}, "dewiki": {"site": "dewiki", "title": "The Modesto Bee", "badges": []}, "enwiki": {"site": "enwiki", "title": "The Modesto Bee", "badges": []}, "nlwiki": {"site": "nlwiki", "title": "The Modesto Bee", "badges": []}}, "pageid": 5324482, "exrest": "The Modesto Bee is a California newspaper, it has about 70 employees and is delivered throughout central California, reaching places such as Modesto, Turlock, Oakdale, Ceres, Patterson and Sonora.", "exhtml": "<p><i><b>The Modesto Bee</b></i> is a California newspaper, it has about 70 employees and is delivered throughout central California, reaching places such as Modesto, Turlock, Oakdale, Ceres, Patterson and Sonora.</p>", "url": "https://en.wikipedia.org/wiki/The_Modesto_Bee", "url_raw": "https://en.wikipedia.org/wiki/The_Modesto_Bee?action=raw", "image": [{"kind": "restbase-original", "width": 232, "height": 428, "url": "https://upload.wikimedia.org/wikipedia/en/8/89/The_Modesto_Bee_front_page.jpg", "file": "The_Modesto_Bee_front_page.jpg"}, {"kind": "restbase-thumb", "width": 232, "height": 428, "url": "https://upload.wikimedia.org/wikipedia/en/8/89/The_Modesto_Bee_front_page.jpg", "file": "The_Modesto_Bee_front_page.jpg"}]}