{"requests": ["wikidata", "labels", "restbase"], "labels": {"P571": "inception", "P31": "instance of", "P2002": "Twitter username", "P495": "country of origin", "Q60": "New York City", "P2003": "Instagram username", "P2013": "Facebook ID", "P291": "place of publication", "P8687": "social media followers", "P1476": "title", "P856": "official website", "Q30": "United States of America", "P646": "Freebase ID", "P9035": "Muck Rack media outlet ID", "P5454": "USNPL ID", "Q11032": "newspaper"}, "wikidata": {"instance of (P31)": "newspaper (Q11032)", "title (P1476)": ["The Tribeca Trib", "Tribeca Trib"], "inception (P571)": "+1994-01-01T00:00:00Z", "USNPL ID (P5454)": "6615", "Facebook ID (P2013)": "tribecatrib", "Twitter username (P2002)": "TribecaTrib", "country of origin (P495)": "United States of America (Q30)", "place of publication (P291)": "New York City (Q60)", "Instagram username (P2003)": "tribecatrib", "official website (P856)": "http://tribecatrib.com", "social media followers (P8687)": [{"amount": "+3714", "unit": "1"}, {"amount": "+3600", "unit": "1"}], "Muck Rack media outlet ID (P9035)": "tribecatrib", "Freebase ID (P646)": "/m/0cn_pk8"}, "wikidata_pageid": 7699854, "aliases": ["Tribeca Trib"], "modified": {"wikidata": "2022-07-12T04:57:00Z"}, "wikibase": "Q7770186", "wikidata_url": "https://www.wikidata.org/wiki/Q7770186", "description": "US newspaper", "label": "The Tribeca Trib", "claims": {"P31": ["Q11032"], "P1476": ["The Tribeca Trib", "Tribeca Trib"], "P571": ["+1994-01-01T00:00:00Z"], "P5454": ["6615"], "P2013": ["tribecatrib"], "P2002": ["TribecaTrib"], "P495": ["Q30"], "P291": ["Q60"], "P2003": ["tribecatrib"], "P856": ["http://tribecatrib.com"], "P8687": [{"amount": "+3714", "unit": "1"}, {"amount": "+3600", "unit": "1"}], "P9035": ["tribecatrib"], "P646": ["/m/0cn_pk8"]}, "title": "The_Tribeca_Trib", "what": "newspaper", "sitelinks": {"enwiki": {"site": "enwiki", "title": "The Tribeca Trib", "badges": []}}}