{"requests": ["wikidata", "labels", "restbase"], "labels": {"P495": "country of origin", "Q61302": "Chihuahua City", "P159": "headquarters location", "P856": "official website", "Q655": "Chihuahua", "P407": "language of work or name", "P8687": "social media followers", "Q58731": "Baja California", "Q1321": "Spanish", "Q96": "Mexico", "P973": "described at URL", "P6375": "street address", "Q11032": "newspaper", "Q17232649": "news website", "P2002": "Twitter username", "P571": "inception", "P31": "instance of", "P921": "main subject", "P17": "country"}, "wikidata": {"country (P17)": "Mexico (Q96)", "official website (P856)": "http://www.el-mexicano.com.mx/", "main subject (P921)": ["Baja California (Q58731)", "Chihuahua (Q655)"], "instance of (P31)": ["news website (Q17232649)", "newspaper (Q11032)"], "language of work or name (P407)": "Spanish (Q1321)", "inception (P571)": "+1947-10-10T00:00:00Z", "described at URL (P973)": "http://sic.gob.mx/ficha.php?table=impresos&table_id=101", "headquarters location (P159)": "Chihuahua City (Q61302)", "country of origin (P495)": "Mexico (Q96)", "street address (P6375)": "Ram\u00f3n Corona 301, Centro, CP 32000, Chihuahua, Chihuahua", "Twitter username (P2002)": "elmexicanonline", "social media followers (P8687)": [{"amount": "+13604", "unit": "1"}, {"amount": "+13606", "unit": "1"}, {"amount": "+14444", "unit": "1"}]}, "wikidata_pageid": 86354254, "aliases": ["el-mexicano.com.mx", "Mexicano"], "modified": {"wikidata": "2022-03-02T17:06:18Z"}, "wikibase": "Q87116216", "wikidata_url": "https://www.wikidata.org/wiki/Q87116216", "description": "Mexican news website", "label": "El Mexicano", "claims": {"P17": ["Q96"], "P856": ["http://www.el-mexicano.com.mx/"], "P921": ["Q58731", "Q655"], "P31": ["Q17232649", "Q11032"], "P407": ["Q1321"], "P571": ["+1947-10-10T00:00:00Z"], "P973": ["http://sic.gob.mx/ficha.php?table=impresos&table_id=101"], "P159": ["Q61302"], "P495": ["Q96"], "P6375": ["Ram\u00f3n Corona 301, Centro, CP 32000, Chihuahua, Chihuahua"], "P2002": ["elmexicanonline"], "P8687": [{"amount": "+13604", "unit": "1"}, {"amount": "+13606", "unit": "1"}, {"amount": "+14444", "unit": "1"}]}, "title": "El_Mexicano", "what": "news website", "sitelinks": {}}