{"requests": ["wikidata", "labels", "restbase"], "labels": {"Q217059": "Unification Church", "P1476": "title", "P3225": "Corporate Number (Japan)", "P407": "language of work or name", "P11496": "CiNii Research ID", "Q624291": "Segye Ilbo", "P1889": "different from", "P271": "CiNii Books author ID", "Q11032": "newspaper", "P31": "instance of", "P7859": "WorldCat Identities ID", "P214": "VIAF ID", "P9035": "Muck Rack media outlet ID", "P571": "inception", "P856": "official website", "P349": "NDL Authority ID", "Q4830453": "business", "P244": "Library of Congress authority ID", "Q8035879": "World Journal", "P127": "owned by", "Q5287": "Japanese", "P2671": "Google Knowledge Graph ID"}, "wikidata": {"official website (P856)": "http://www.worldtimes.co.jp/", "VIAF ID (P214)": "157147461", "NDL Authority ID (P349)": "00299522", "Library of Congress authority ID (P244)": "n83199064", "CiNii Books author ID (P271)": "DA0148759X", "owned by (P127)": "Unification Church (Q217059)", "WorldCat Identities ID (P7859)": "lccn-n83199064", "Muck Rack media outlet ID (P9035)": "worldtimesco", "instance of (P31)": ["business (Q4830453)", "newspaper (Q11032)"], "Google Knowledge Graph ID (P2671)": ["/g/120j8j88", "/g/121hxwtm"], "different from (P1889)": ["Segye Ilbo (Q624291)", "World Journal (Q8035879)"], "title (P1476)": "\u4e16\u754c\u65e5\u5831", "language of work or name (P407)": "Japanese (Q5287)", "inception (P571)": "+1975-00-00T00:00:00Z", "Corporate Number (Japan) (P3225)": "6011401014474", "CiNii Research ID (P11496)": "1140282266672799744"}, "wikidata_pageid": 12500382, "modified": {"wikidata": "2023-03-23T03:14:53Z"}, "wikibase": "Q11362392", "wikidata_url": "https://www.wikidata.org/wiki/Q11362392", "description": null, "label": "Sekai Nippo", "claims": {"P856": ["http://www.worldtimes.co.jp/"], "P214": ["157147461"], "P349": ["00299522"], "P244": ["n83199064"], "P271": ["DA0148759X"], "P127": ["Q217059"], "P7859": ["lccn-n83199064"], "P9035": ["worldtimesco"], "P31": ["Q4830453", "Q11032"], "P2671": ["/g/120j8j88", "/g/121hxwtm"], "P1889": ["Q624291", "Q8035879"], "P1476": ["\u4e16\u754c\u65e5\u5831"], "P407": ["Q5287"], "P571": ["+1975-00-00T00:00:00Z"], "P3225": ["6011401014474"], "P11496": ["1140282266672799744"]}, "title": "Sekai_Nippo", "what": "business", "sitelinks": {"enwiki": {"site": "enwiki", "title": "Sekai Nippo", "badges": []}, "jawiki": {"site": "jawiki", "title": "\u4e16\u754c\u65e5\u5831 (\u65e5\u672c)", "badges": []}, "kowiki": {"site": "kowiki", "title": "\uc138\uacc4\uc77c\ubcf4 (\uc77c\ubcf8)", "badges": []}, "ruwiki": {"site": "ruwiki", "title": "\u0421\u044d\u043a\u0430\u0439 \u041d\u0438\u043f\u043f\u043e", "badges": []}, "zhwiki": {"site": "zhwiki", "title": "\u4e16\u754c\u65e5\u5831 (\u65e5\u672c)", "badges": []}}}